oracle_json_field/__init__.py
oracle_json_field/admin.py
oracle_json_field/apps.py
oracle_json_field/constants.py
oracle_json_field/encoders.py
oracle_json_field/fields.py
oracle_json_field/managers.py
oracle_json_field/models.py
oracle_json_field/tests.py
oracle_json_field/views.py
oracle_json_field-0.0.7.dist-info/LICENSE
oracle_json_field-0.0.7.dist-info/METADATA
oracle_json_field-0.0.7.dist-info/WHEEL
oracle_json_field-0.0.7.dist-info/top_level.txt
oracle_json_field-0.0.7.dist-info/RECORD
