Metadata-Version: 2.1
Name: oracle-json-field
Version: 0.0.7
Summary: A JSON field for Oracle backends.
Home-page: UNKNOWN
Author: Vackar Afzal
Author-email: vafzal@exscientia.co.uk
License: MIT
Platform: UNKNOWN
Classifier: Environment :: Web Environment
Classifier: Intended Audience :: Developers
Classifier: Operating System :: OS Independent
Classifier: Programming Language :: Python
Classifier: Programming Language :: Python :: 3
Classifier: Programming Language :: Python :: 3.3
Classifier: Programming Language :: Python :: 3.4
Classifier: Programming Language :: Python :: 3.5
Classifier: Programming Language :: Python :: 3.6
Classifier: Framework :: Django
Requires-Dist: Django (>=2.0.0)
